{
  "customers": [
    {
      "name": "Alice Brown",
      "email": "alice.brown@example.com",
      "phone": "555-9876",
      "address": {
        "street": "456 Bakery Ave",
        "city": "Sweetville",
        "state": "CA",
        "zip": "90001"
      },
      "created_at": "2024-09-23T12:30:00Z"
    },
    {
      "name": "Carlos Hernandez",
      "email": "carlos.hernandez@example.com",
      "phone": "555-2345",
      "address": {
        "street": "789 Pastry St",
        "city": "Dessertown",
        "state": "TX",
        "zip": "75001"
      },
      "created_at": "2024-09-20T08:45:00Z"
    }
  ],
  "products": [
    {
      "name": "Chocolate Cake",
      "description": "Rich chocolate cake with layers of creamy chocolate frosting",
      "price": 25.00,
      "category": "cakes",
      "stock_quantity": 15
    },
    {
      "name": "Vanilla Cupcakes",
      "description": "Fluffy vanilla cupcakes topped with buttercream frosting",
      "price": 3.50,
      "category": "cupcakes",
      "stock_quantity": 50
    },
    {
      "name": "Cinnamon Rolls",
      "description": "Soft, warm cinnamon rolls with cream cheese icing",
      "price": 4.00,
      "category": "pastries",
      "stock_quantity": 30
    },
    {
      "name": "Apple Pie",
      "description": "Classic apple pie with a buttery crust and spiced apple filling",
      "price": 20.00,
      "category": "pies",
      "stock_quantity": 10
    },
    {
      "name": "Chocolate Chip Cookies",
      "description": "Chewy cookies packed with chocolate chips",
      "price": 1.50,
      "category": "cookies",
      "stock_quantity": 100
    }
  ],
  "invoices": [
    {
      "customer_name": "Alice Brown",
      "date": "2024-09-23",
      "items": [
        {
          "product_name": "Chocolate Cake",
          "quantity": 1,
          "price": 25.00,
          "total": 25.00
        },
        {
          "product_name": "Cinnamon Rolls",
          "quantity": 3,
          "price": 4.00,
          "total": 12.00
        }
      ],
      "subtotal": 37.00,
      "tax": 2.96,
      "total": 39.96,
      "status": "pending",
      "payment_method": "cash"
    },
    {
      "customer_name": "Carlos Hernandez",
      "date": "2024-09-20",
      "items": [
        {
          "product_name": "Vanilla Cupcakes",
          "quantity": 6,
          "price": 3.50,
          "total": 21.00
        },
        {
          "product_name": "Apple Pie",
          "quantity": 1,
          "price": 20.00,
          "total": 20.00
        }
      ],
      "subtotal": 41.00,
      "tax": 3.28,
      "total": 44.28,
      "status": "paid",
      "payment_method": "credit_card",
      "paid_at": "2024-09-20T12:30:00Z"
    }
  ],
  "payments": [
    {
      "invoice_date": "2024-09-20",
      "amount": 44.28,
      "method": "credit_card",
      "status": "completed",
      "date": "2024-09-20T12:30:00Z"
    }
  ]
}